pymako/__init__.py
pymako/catalog.py
pymako/client.py
pymako/exceptions.py
pymako/kv.py
pymako/status.py
pymako-0.0.2.dist-info/LICENSE
pymako-0.0.2.dist-info/METADATA
pymako-0.0.2.dist-info/WHEEL
pymako-0.0.2.dist-info/top_level.txt
pymako-0.0.2.dist-info/RECORD
